Workbook

Sheet Q1
A1: Initial Date | B1: 11-12-24
A2: Maturity Date | B2: 46038
A3: S0 | B3: 301.76 | D3: ST | E3: Probability
A4: N | B4: 100 | D4: 377.70451 | E4: 0.11380143
A5: r(annual) | B5: 0.0404 | D5: 336.04478 | E5: 0.32853206
A6: Sigma | B6: 0.1115 | D6: 298.98 | E6: 0.3556633
A7: Didvend | B7: 0 | D7: 266.00336 | E7: 0.17112672
A8: Day count fraction(T) | B8: =(B2-B1)/365 -> 1.0986301 | D8: 236.66395 | E8: 0.030876487
A9: Discount Factor | B9: =1/(1+$B$5)^($B$8) -> 0.95742152
A10: Principal Protection Amount (90% of N) | B10: =0.9*B4 -> 90
A11: Present Value of Protection | B11: =B10*B9 -> 86.167937
A13: K1 | B13: Put(K1) | C13: K2 | D13: Call(K2) | E13: Sum(P+C) | F13: N/S0 | G13: Total Option Cost | H13: Profit Margin of banks
B14: =B4/B3 -> 0.33138918
A16: 280 | B16: 14.05 | C16: 305 | D16: 26.1 | E16: =D16+B16 -> 40.15 | F16: =$B$4/$B$3 -> 0.33138918 | G16: =(B16+D16)*$B$14 -> 13.305276 | H16: =($B$4 - $B$11) - G16 -> 0.52678762
A17: 290 | B17: 15.75 | C17: 310 | D17: 23.4 | E17: =D17+B17 -> 39.15 | F17: =$B$4/$B$3 -> 0.33138918 | G17: =(B17+D17)*$B$14 -> 12.973887 | H17: =($B$4 - $B$11) - G17 -> 0.8581768
A18: 295 | B18: 17.8 | C18: 315 | D18: 21.1 | E18: =D18+B18 -> 38.9 | F18: =$B$4/$B$3 -> 0.33138918 | G18: =(B18+D18)*$B$14 -> 12.891039 | H18: =($B$4 - $B$11) - G18 -> 0.9410241
B20: ST | C20: 377.70451 | D20: 336.04478 | E20: 298.98 | F20: 266.00336 | G20: 236.66395
C21: Payoff of Investors | D21: Payoff of Investors | E21: Payoff of Investors | F21: Payoff of Investors | G21: Payoff of Investors | H21: Expected Pyaoff | I21: Profit Margin of banks
B22: K1=280 K2=305 | C22: =90+IF($D$4<A16,F16*(A16-$D$4),IF($D$4>'Q1'!$C16,F16*($D$4-A16),0)) -> 122.37822 | D22: =90+IF($D$5<A16,F16*(A16-$D$5),IF($D$5>'Q1'!$C16,F16*($D$5-A16),0)) -> 108.57263 | E22: =90+IF($D$6<A16,F16*(A16-$D$6),IF($D$6>'Q1'!$C16,F16*($D$56-A16),0)) -> 90 | F22: =90+IF($D$7<A16,F16*(A16-$D$7),IF($D$7>'Q1'!$C16,F16*($D$7-A16),0)) -> 94.638335 | G22: =90+IF($D$8<A16,F16*(A16-$D$8),IF($D$8>'Q1'!$C16,F16*($D$8-A16),0)) -> 104.3611 | H22: =C22*$E$4+D22*$E$5+E22*$E$6+F22*$E$7+G22*$E$8 -> 101.02356 | I22: 0.52678762
B23: K1=290 K2=310 | C23: =90+IF($D$4<A17,F17*(A17-$D$4),IF($D$4>'Q1'!$C17,F17*($D$4-A17),0)) -> 119.06433 | D23: =90+IF($D$5<A17,F17*(A17-$D$5),IF($D$5>'Q1'!$C17,F17*($D$5-A17),0)) -> 105.25874 | E23: =90+IF($D$6<A17,F17*(A17-$D$6),IF($D$6>'Q1'!$C17,F17*($D$56-A17),0)) -> 90 | F23: =90+IF($D$7<A17,F17*(A17-$D$7),IF($D$7>'Q1'!$C17,F17*($D$7-A17),0)) -> 97.952227 | G23: =90+IF($D$8<A17,F17*(A17-$D$8),IF($D$8>'Q1'!$C17,F17*($D$8-A17),0)) -> 107.67499 | H23: =C23*$E$4+D23*$E$5+E23*$E$6+F23*$E$7+G23*$E$8 -> 100.22713 | I23: 0.8581768
B24: K1=295 K2=315 | C24: =90+IF($D$4<A18,F18*(A18-$D$4),IF($D$4>'Q1'!$C18,F18*($D$4-A18),0)) -> 117.40738 | D24: =90+IF($D$5<A18,F18*(A18-$D$5),IF($D$5>'Q1'!$C18,F18*($D$5-A18),0)) -> 103.6018 | E24: =90+IF($D$6<A18,F18*(A18-$D$6),IF($D$6>'Q1'!$C18,F18*($D$56-A18),0)) -> 90 | F24: =90+IF($D$7<A18,F18*(A18-$D$7),IF($D$7>'Q1'!$C18,F18*($D$7-A18),0)) -> 99.609173 | G24: =90+IF($D$8<A18,F18*(A18-$D$8),IF($D$8>'Q1'!$C18,F18*($D$8-A18),0)) -> 109.33194 | H24: =C24*$E$4+D24*$E$5+E24*$E$6+F24*$E$7+G24*$E$8 -> 99.828914 | I24: 0.9410241

Sheet Q2
A1: InitiaH Date | B1: 45637 | G1: ST | H1: ProbabiHity
A2: Maturity Date | B2: 46038 | G2: 377.70451 | H2: 0.11380143
A3: S0 | B3: 301.76 | G3: 336.04478 | H3: 0.32853206
A4: N | B4: 100 | G4: 298.98 | H4: 0.3556633
A5: r(annuaH) | B5: 0.0404 | G5: 266.00336 | H5: 0.17112672
A6: Sigma | B6: 0.1115 | G6: 236.66395 | H6: 0.030876487
A7: Didvend | B7: 0
A8: Day count fraction(T) | B8: =(B2-B1)/365 -> 1.0986301
A9: Discount Factor | B9: 0.95569233
A10: PrincipaH Protection Amount (100% of N) | B10: 100
A11: Present VaHue of Bond | B11: =B9*B10 -> 95.569233
A12: Price of digital call(D) | B12: 0.59
F13: m1 | H13: m2 | J13: m3
A14: Outcome of m | B14: Value of m | C14: Cost of buying digitaH caHH | D14: Profit Margin of bank | E14: ST | F14: Payoff of Investors | G14: Expected Payoff | H14: Payoff of Investors | I14: Expected Payoff | J14: Payoff of Investors | K14: Expected Payoff
A15: m1 | B15: =($B$4-$B$11)/($B$12*$B$4) -> 0.075097746 | C15: =$B$12*$B15*$B$4 -> 4.430767 | D15: =$B$4-$B$11-C15 -> 0 | E15: 377.70451 | F15: =100+IF(G2>=$B$3,$B$15*$B$4,IF(G2<$B$3,0)) -> 107.50977 | G15: =F15*H2+F16*H3+F17*H4+F18*H5+F19*H6 -> 103.32182 | H15: =100+IF(G2>=$B$3,$B$16*$B$4,IF(G2<$B$3,0)) -> 107 | I15: =H15*H2+H16*H3+H17*H4+H18*H5+H19*H6 -> 103.09633 | J15: =100+IF(G2>=$B$3,$B$17*$B$4,IF(G2<$B$3,0)) -> 106 | K15: =J15*H2+J16*H3+J17*H4+J18*H5+J19*H6 -> 102.654
A16: m2 | B16: 0.07 | C16: =$B$12*$B16*$B$4 -> 4.13 | D16: =$B$4-$B$11-C16 -> 0.30076702 | E16: 336.04478 | F16: =100+IF(G3>=$B$3,$B$15*$B$4,IF(G3<$B$3,0)) -> 107.50977 | H16: =100+IF(G3>=$B$3,$B$16*$B$4,IF(G3<$B$3,0)) -> 107 | J16: =100+IF(G3>=$B$3,$B$17*$B$4,IF(G3<$B$3,0)) -> 106
A17: m3 | B17: 0.06 | C17: =$B$12*$B17*$B$4 -> 3.54 | D17: =$B$4-$B$11-C17 -> 0.89076702 | E17: 298.98 | F17: =100+IF(G4>=$B$3,$B$15*$B$4,IF(G4<$B$3,0)) -> 100 | H17: =100+IF(G4>=$B$3,$B$16*$B$4,IF(G4<$B$3,0)) -> 100 | J17: =100+IF(G4>=$B$3,$B$17*$B$4,IF(G4<$B$3,0)) -> 100
A18: m4 | B18: 0.05 | C18: =$B$12*$B18*$B$4 -> 2.95 | D18: =$B$4-$B$11-C18 -> 1.480767 | E18: 266.00336 | F18: =100+IF(G5>=$B$3,$B$15*$B$4,IF(G5<$B$3,0)) -> 100 | H18: =100+IF(G5>=$B$3,$B$16*$B$4,IF(G5<$B$3,0)) -> 100 | J18: =100+IF(G5>=$B$3,$B$17*$B$4,IF(G5<$B$3,0)) -> 100
A19: m5 | B19: 0.04 | C19: =$B$12*$B19*$B$4 -> 2.36 | D19: =$B$4-$B$11-C19 -> 2.070767 | E19: 236.66395 | F19: =100+IF(G6>=$B$3,$B$15*$B$4,IF(G6<$B$3,0)) -> 100 | H19: =100+IF(G6>=$B$3,$B$16*$B$4,IF(G6<$B$3,0)) -> 100 | J19: =100+IF(G6>=$B$3,$B$17*$B$4,IF(G6<$B$3,0)) -> 100
F20: m4 | H20: m5
F21: Payoff of Investors | G21: Expected Payoff | H21: Payoff of Investors | I21: Expected Payoff
A22: Results | B22: Expected Payoff | C22: Profit Margin of Bank | F22: =100+IF(G2>=$B$3,$B$18*$B$4,IF(G2<$B$3,0)) -> 105 | G22: =F22*H2+F23*H3+F24*H4+F25*H5+F26*H6 -> 102.21167 | H22: =100+IF(G2>=$B$3,$B$19*$B$4,IF(G2<$B$3,0)) -> 104 | I22: =H22*H2+H23*H3+H24*H4+H25*H5+H26*H6 -> 101.76933
A23: m1 | B23: =G15 -> 103.32182 | C23: =D15 -> 0 | F23: =100+IF(G3>=$B$3,$B$18*$B$4,IF(G3<$B$3,0)) -> 105 | H23: =100+IF(G3>=$B$3,$B$19*$B$4,IF(G3<$B$3,0)) -> 104
A24: m2 | B24: =I15 -> 103.09633 | C24: =D16 -> 0.30076702 | F24: =100+IF(G4>=$B$3,$B$18*$B$4,IF(G4<$B$3,0)) -> 100 | H24: =100+IF(G4>=$B$3,$B$19*$B$4,IF(G4<$B$3,0)) -> 100
A25: m3 | B25: =K15 -> 102.654 | C25: =D17 -> 0.89076702 | F25: =100+IF(G5>=$B$3,$B$18*$B$4,IF(G5<$B$3,0)) -> 100 | H25: =100+IF(G5>=$B$3,$B$19*$B$4,IF(G5<$B$3,0)) -> 100
A26: m4 | B26: =G22 -> 102.21167 | C26: =D18 -> 1.480767 | F26: =100+IF(G6>=$B$3,$B$18*$B$4,IF(G6<$B$3,0)) -> 100 | H26: =100+IF(G6>=$B$3,$B$19*$B$4,IF(G6<$B$3,0)) -> 100
A27: m5 | B27: =I22 -> 101.76933 | C27: =D19 -> 2.070767
